JingtongSklearnHeTensorflowYucexingFenxiChuyiFix1/README.md
JingtongSklearnHeTensorflowYucexingFenxiChuyiFix1/__init__.py
JingtongSklearnHeTensorflowYucexingFenxiChuyiFix1/__main__.py
JingtongSklearnHeTensorflowYucexingFenxiChuyiFix1/file.epub
JingtongSklearnHeTensorflowYucexingFenxiChuyiFix1/index.html
JingtongSklearnHeTensorflowYucexingFenxiChuyiFix1/css/__init__.py
JingtongSklearnHeTensorflowYucexingFenxiChuyiFix1/css/annotations.css
JingtongSklearnHeTensorflowYucexingFenxiChuyiFix1/css/main.css
JingtongSklearnHeTensorflowYucexingFenxiChuyiFix1/css/normalize.css
JingtongSklearnHeTensorflowYucexingFenxiChuyiFix1/css/popup.css
JingtongSklearnHeTensorflowYucexingFenxiChuyiFix1/font/__init__.py
JingtongSklearnHeTensorflowYucexingFenxiChuyiFix1/font/fontello.eot
JingtongSklearnHeTensorflowYucexingFenxiChuyiFix1/font/fontello.svg
JingtongSklearnHeTensorflowYucexingFenxiChuyiFix1/font/fontello.ttf
JingtongSklearnHeTensorflowYucexingFenxiChuyiFix1/font/fontello.woff
JingtongSklearnHeTensorflowYucexingFenxiChuyiFix1/img/__init__.py
JingtongSklearnHeTensorflowYucexingFenxiChuyiFix1/img/annotator-glyph-sprite.png
JingtongSklearnHeTensorflowYucexingFenxiChuyiFix1/img/annotator-icon-sprite.png
JingtongSklearnHeTensorflowYucexingFenxiChuyiFix1/img/apple-touch-icon.png
JingtongSklearnHeTensorflowYucexingFenxiChuyiFix1/img/cancelfullscreen.png
JingtongSklearnHeTensorflowYucexingFenxiChuyiFix1/img/close.png
JingtongSklearnHeTensorflowYucexingFenxiChuyiFix1/img/fullscreen.png
JingtongSklearnHeTensorflowYucexingFenxiChuyiFix1/img/loader.gif
JingtongSklearnHeTensorflowYucexingFenxiChuyiFix1/img/menu-icon.png
JingtongSklearnHeTensorflowYucexingFenxiChuyiFix1/img/save.png
JingtongSklearnHeTensorflowYucexingFenxiChuyiFix1/img/saved.png
JingtongSklearnHeTensorflowYucexingFenxiChuyiFix1/img/settings-s.png
JingtongSklearnHeTensorflowYucexingFenxiChuyiFix1/img/settings.png
JingtongSklearnHeTensorflowYucexingFenxiChuyiFix1/img/star.png
jingtong_sklearn_he_tensorflow_yucexing_fenxi_chuyi_fix1-2025.3.25.1.dist-info/METADATA
jingtong_sklearn_he_tensorflow_yucexing_fenxi_chuyi_fix1-2025.3.25.1.dist-info/WHEEL
jingtong_sklearn_he_tensorflow_yucexing_fenxi_chuyi_fix1-2025.3.25.1.dist-info/entry_points.txt
jingtong_sklearn_he_tensorflow_yucexing_fenxi_chuyi_fix1-2025.3.25.1.dist-info/top_level.txt
jingtong_sklearn_he_tensorflow_yucexing_fenxi_chuyi_fix1-2025.3.25.1.dist-info/RECORD
